pybaserepo/__init__.py
pybaserepo/__main__.py
pybaserepo-0.2.2.dist-info/METADATA
pybaserepo-0.2.2.dist-info/LICENSE
pybaserepo-0.2.2.dist-info/WHEEL
pybaserepo-0.2.2.dist-info/RECORD
