Metadata-Version: 2.1
Name: pybaserepo
Version: 0.2.2
Summary: base repo config
License: LICENSE
Author: Ivan Lamperti
Author-email: ivan.lamperti.work@gmail.com
Requires-Python: >=3.10,<4.0
Classifier: Development Status :: 2 - Pre-Alpha
Classifier: License :: Other/Proprietary License
Classifier: Programming Language :: Python :: 3
Classifier: Programming Language :: Python :: 3.10
Classifier: Programming Language :: Python :: 3.11
Requires-Dist: click (>=8.1.3,<9.0.0)
